jwt/__init__.py
jwt/jwt.py
jwtv2-1.0.1.dist-info/licenses/LICENSE
jwtv2-1.0.1.dist-info/METADATA
jwtv2-1.0.1.dist-info/WHEEL
jwtv2-1.0.1.dist-info/top_level.txt
jwtv2-1.0.1.dist-info/RECORD
