Metadata-Version: 2.4
Name: jwtv2
Version: 1.0.1
Summary: A package for CTF Challenge
Author-email: Example Author <author@1337.com>
License-Expression: MIT
Project-URL: Homepage, http://localhost:1337/
Project-URL: Issues, https://localhost:1337/issues
Classifier: Programming Language :: Python :: 3
Classifier: Operating System :: OS Independent
Requires-Python: >=3.1
License-File: LICENSE
Dynamic: license-file
